Workbook
Name Slicer_Diabetic_Status1: #N/A
Name Slicer_Smoker: #N/A
Name Slicer_Weight_Status1: #N/A

Sheet Customer Name
A1: Customer ID | B1: Title | C1: First Name | D1: Last Name
A2: Id1 | B2: Ms | C2: Kelly | D2: Hawks
A3: Id2 | B3: Mr | C3: Matthew D | D3: Lehner
A4: Id3 | B4: Mr | C4: Phil | D4: Lu
A5: Id4 | B5: Ms | C5: Kelsey | D5: Osborne
A6: Id5 | B6: Mr | C6: Kristyn | D6: Kadala
A7: Id6 | B7: Mr | C7: Russell B | D7: Baker
A8: Id7 | B8: Ms | C8: Scott | D8: Macpherson
A9: Id8 | B9: Mr | C9: Stephen | D9: Hallman
A10: Id9 | B10: Mr | C10: Patrick R | D10: Moran
A11: Id10 | B11: Ms | C11: Brooke N | D11: Benner
A12: Id11 | B12: Mr | C12: Paola Andrea | D12: Fierro Vargas
... A2336: Id2335 | B2336: Ms | C2336: Aaron K | D2336: German

Sheet Medical Examination
A1: Customer ID | B1: BMI | C1: HBA1C | D1: Heart Issues | E1: Any Transplants | F1: Cancer history | G1: NumberOfMajorSurgeries | H1: smoker | I1: Weight Status | J1: Diabetis Status
A2: Id1 | B2: 47.41 | C2: 7.47 | D2: No | E2: No | F2: No | G2: 0 | H2: yes | I2: =IF(B2>=30,"Obesity",IF(B2>=25,"Overweight",IF(B2>18.5,"Normal Weight","Under Weight"))) -> Obesity | J2: =IF(Table1_1[[#This Row],[HBA1C]]>=6.5,"Diabetic",IF(Table1_1[[#This Row],[HBA1C]]>=5.7,"Prediabetic","Normal")) -> Diabetic
A3: Id2 | B3: 30.36 | C3: 5.77 | D3: No | E3: No | F3: No | G3: 0 | H3: yes | I3: =IF(B3>=30,"Obesity",IF(B3>=25,"Overweight",IF(B3>18.5,"Normal Weight","Under Weight"))) -> Obesity | J3: =IF(Table1_1[[#This Row],[HBA1C]]>=6.5,"Diabetic",IF(Table1_1[[#This Row],[HBA1C]]>=5.7,"Prediabetic","Normal")) -> Prediabetic
A4: Id3 | B4: 34.485 | C4: 11.87 | D4: yes | E4: No | F4: No | G4: 2 | H4: yes | I4: =IF(B4>=30,"Obesity",IF(B4>=25,"Overweight",IF(B4>18.5,"Normal Weight","Under Weight"))) -> Obesity | J4: =IF(Table1_1[[#This Row],[HBA1C]]>=6.5,"Diabetic",IF(Table1_1[[#This Row],[HBA1C]]>=5.7,"Prediabetic","Normal")) -> Diabetic
A5: Id4 | B5: 38.095 | C5: 6.05 | D5: No | E5: No | F5: No | G5: 0 | H5: yes | I5: =IF(B5>=30,"Obesity",IF(B5>=25,"Overweight",IF(B5>18.5,"Normal Weight","Under Weight"))) -> Obesity | J5: =IF(Table1_1[[#This Row],[HBA1C]]>=6.5,"Diabetic",IF(Table1_1[[#This Row],[HBA1C]]>=5.7,"Prediabetic","Normal")) -> Prediabetic
A6: Id5 | B6: 35.53 | C6: 5.45 | D6: No | E6: No | F6: No | G6: 0 | H6: yes | I6: =IF(B6>=30,"Obesity",IF(B6>=25,"Overweight",IF(B6>18.5,"Normal Weight","Under Weight"))) -> Obesity | J6: =IF(Table1_1[[#This Row],[HBA1C]]>=6.5,"Diabetic",IF(Table1_1[[#This Row],[HBA1C]]>=5.7,"Prediabetic","Normal")) -> Normal
A7: Id6 | B7: 32.8 | C7: 6.59 | D7: No | E7: No | F7: No | G7: 0 | H7: yes | I7: =IF(B7>=30,"Obesity",IF(B7>=25,"Overweight",IF(B7>18.5,"Normal Weight","Under Weight"))) -> Obesity | J7: =IF(Table1_1[[#This Row],[HBA1C]]>=6.5,"Diabetic",IF(Table1_1[[#This Row],[HBA1C]]>=5.7,"Prediabetic","Normal")) -> Diabetic
A8: Id7 | B8: 36.4 | C8: 6.07 | D8: No | E8: No | F8: No | G8: 0 | H8: yes | I8: =IF(B8>=30,"Obesity",IF(B8>=25,"Overweight",IF(B8>18.5,"Normal Weight","Under Weight"))) -> Obesity | J8: =IF(Table1_1[[#This Row],[HBA1C]]>=6.5,"Diabetic",IF(Table1_1[[#This Row],[HBA1C]]>=5.7,"Prediabetic","Normal")) -> Prediabetic
A9: Id8 | B9: 36.96 | C9: 7.93 | D9: No | E9: No | F9: No | G9: 3 | H9: yes | I9: =IF(B9>=30,"Obesity",IF(B9>=25,"Overweight",IF(B9>18.5,"Normal Weight","Under Weight"))) -> Obesity | J9: =IF(Table1_1[[#This Row],[HBA1C]]>=6.5,"Diabetic",IF(Table1_1[[#This Row],[HBA1C]]>=5.7,"Prediabetic","Normal")) -> Diabetic
A10: Id9 | B10: 41.14 | C10: 9.58 | D10: yes | E10: No | F10: Yes | G10: 1 | H10: yes | I10: =IF(B10>=30,"Obesity",IF(B10>=25,"Overweight",IF(B10>18.5,"Normal Weight","Under Weight"))) -> Obesity | J10: =IF(Table1_1[[#This Row],[HBA1C]]>=6.5,"Diabetic",IF(Table1_1[[#This Row],[HBA1C]]>=5.7,"Prediabetic","Normal")) -> Diabetic
A11: Id10 | B11: 38.06 | C11: 10.79 | D11: No | E11: No | F11: No | G11: 0 | H11: yes | I11: =IF(B11>=30,"Obesity",IF(B11>=25,"Overweight",IF(B11>18.5,"Normal Weight","Under Weight"))) -> Obesity | J11: =IF(Table1_1[[#This Row],[HBA1C]]>=6.5,"Diabetic",IF(Table1_1[[#This Row],[HBA1C]]>=5.7,"Prediabetic","Normal")) -> Diabetic
A12: Id11 | B12: 37.7 | C12: 5.96 | D12: yes | E12: No | F12: No | G12: 2 | H12: yes | I12: =IF(B12>=30,"Obesity",IF(B12>=25,"Overweight",IF(B12>18.5,"Normal Weight","Under Weight"))) -> Obesity | J12: =IF(Table1_1[[#This Row],[HBA1C]]>=6.5,"Diabetic",IF(Table1_1[[#This Row],[HBA1C]]>=5.7,"Prediabetic","Normal")) -> Prediabetic
A13: Id12 | B13: 42.13 | C13: 11.9 | D13: No | E13: No | F13: No | G13: 0 | H13: yes | I13: =IF(B13>=30,"Obesity",IF(B13>=25,"Overweight",IF(B13>18.5,"Normal Weight","Under Weight"))) -> Obesity | J13: =IF(Table1_1[[#This Row],[HBA1C]]>=6.5,"Diabetic",IF(Table1_1[[#This Row],[HBA1C]]>=5.7,"Prediabetic","Normal")) -> Diabetic
... A2336: Id2335 | B2336: 17.58 | C2336: 4.51 | D2336: No | E2336: No | F2336: No | G2336: 1 | H2336: No | I2336: =IF(B2336>=30,"Obesity",IF(B2336>=25,"Overweight",IF(B2336>18.5,"Normal Weight","Under Weight"))) -> Under Weight | J2336: =IF(Table1_1[[#This Row],[HBA1C]]>=6.5,"Diabetic",IF(Table1_1[[#This Row],[HBA1C]]>=5.7,"Prediabetic","Normal")) -> Normal

Sheet Hospital details
A1: Customer ID | B1: Date of Birth | C1: Children | D1: Charges | E1: Hospital tier | F1: City tier | G1: State ID | H1: Age | K1: 45085
A2: Id1 | B2: 25123 | C2: 0 | D2: 63770.43 | E2: tier - 1 | F2: tier - 3 | G2: R1013 | H2: =DATEDIF(Table4_2[[#This Row],[Date of Birth]],$K$1,"y") -> 54
A3: Id10 | B3: 28853 | C3: 0 | D3: 48885.14 | E3: tier - 1 | F3: tier - 2 | G3: R1013 | H3: =DATEDIF(Table4_2[[#This Row],[Date of Birth]],$K$1,"y") -> 44
A4: Id100 | B4: 28303 | C4: 2 | D4: 40284.38 | E4: tier - 1 | F4: tier - 3 | G4: R1012 | H4: =DATEDIF(Table4_2[[#This Row],[Date of Birth]],$K$1,"y") -> 45
A5: Id1000 | B5: 32859 | C5: 3 | D5: 11250.43 | E5: tier - 3 | F5: tier - 2 | G5: R1026 | H5: =DATEDIF(Table4_2[[#This Row],[Date of Birth]],$K$1,"y") -> 33
A6: Id1001 | B6: 25567 | C6: 2 | D6: 11244.38 | E6: tier - 3 | F6: tier - 1 | G6: R1016 | H6: =DATEDIF(Table4_2[[#This Row],[Date of Birth]],$K$1,"y") -> 53
A7: Id1002 | B7: 27939 | C7: 2 | D7: 11217.35 | E7: tier - 3 | F7: tier - 2 | G7: R1025 | H7: =DATEDIF(Table4_2[[#This Row],[Date of Birth]],$K$1,"y") -> 46
A8: Id1003 | B8: 25733 | C8: 2 | D8: 11187.66 | E8: tier - 3 | F8: tier - 2 | G8: R1012 | H8: =DATEDIF(Table4_2[[#This Row],[Date of Birth]],$K$1,"y") -> 52
A9: Id1004 | B9: 26545 | C9: 0 | D9: 11186.2 | E9: tier - 3 | F9: tier - 2 | G9: R1021 | H9: =DATEDIF(Table4_2[[#This Row],[Date of Birth]],$K$1,"y") -> 50
A10: Id1005 | B10: 24325 | C10: 0 | D10: 11165.42 | E10: tier - 3 | F10: tier - 1 | G10: R1016 | H10: =DATEDIF(Table4_2[[#This Row],[Date of Birth]],$K$1,"y") -> 56
A11: Id1006 | B11: 25379 | C11: 2 | D11: 11163.57 | E11: tier - 3 | F11: tier - 2 | G11: R1011 | H11: =DATEDIF(Table4_2[[#This Row],[Date of Birth]],$K$1,"y") -> 53
A12: Id1007 | B12: 25537 | C12: 2 | D12: 11150.78 | E12: tier - 3 | F12: tier - 2 | G12: R1011 | H12: =DATEDIF(Table4_2[[#This Row],[Date of Birth]],$K$1,"y") -> 53
A13: Id1008 | B13: 29453 | C13: 2 | D13: 11103.33 | E13: tier - 3 | F13: tier - 1 | G13: R1021 | H13: =DATEDIF(Table4_2[[#This Row],[Date of Birth]],$K$1,"y") -> 42
... A2344: N/A | B2344: 33564 | C2344: 2 | D2344: 38711 | E2344: tier - 1 | F2344: tier - 3 | G2344: R1011 | H2344: =DATEDIF(Table4_2[[#This Row],[Date of Birth]],$K$1,"y") -> 31

Sheet Healthcare
A1: Customer ID | B1: Title | C1: First Name | D1: Last Name | E1: BMI | F1: HBAIC | G1: Heart Disease | H1: Any Transplants | I1: Cancer History | J1: Number of major Surgeries | K1: Smoker | L1: Weight Status | M1: Diabetic Status | N1: Date of Birth | O1: Charges | P1: Hospital Tier | Q1: City Tier | R1: State ID | S1: Age
A2: Id1 | B2: {=_xlfn.XLOOKUP(_xlfn.SINGLE(A:A),'Customer Name'!A:A,Table14_3[[#All],[Title]])} -> Ms | C2: {=_xlfn.XLOOKUP(_xlfn.SINGLE(A:A),'Customer Name'!A:A,Table14_3[[#All],[First Name]])} -> Kelly | D2: {=_xlfn.XLOOKUP(_xlfn.SINGLE(A:A),'Customer Name'!A:A,Table14_3[[#All],[Last Name]])} -> Hawks | E2: =_xlfn.XLOOKUP(A:A,'Medical Examination'!A:A,'Medical Examination'!B:B) -> 47.41 | F2: =_xlfn.XLOOKUP(A:A,'Medical Examination'!A:A,'Medical Examination'!C:C) -> 7.47 | G2: =_xlfn.XLOOKUP(A:A,'Medical Examination'!A:A,'Medical Examination'!D:D) -> No | H2: =_xlfn.XLOOKUP(A:A,'Medical Examination'!A:A,'Medical Examination'!E:E) -> No | I2: =_xlfn.XLOOKUP(A:A,'Medical Examination'!A:A,'Medical Examination'!F:F) -> No | J2: =_xlfn.XLOOKUP(A:A,'Medical Examination'!A:A,'Medical Examination'!G:G) -> 0 | K2: =_xlfn.XLOOKUP(A:A,'Medical Examination'!A:A,'Medical Examination'!H:H) -> yes | L2: =_xlfn.XLOOKUP(A:A,'Medical Examination'!A:A,'Medical Examination'!I:I) -> Obesity | M2: =_xlfn.XLOOKUP(A:A,'Medical Examination'!A:A,'Medical Examination'!J:J) -> Diabetic | N2: =_xlfn.XLOOKUP(Healthcare!A:A,Table4_2[Customer ID],Table4_2[Date of Birth]) -> 25123 | O2: =_xlfn.XLOOKUP(A:A,Table4_2[Customer ID],Table4_2[Charges]) -> 63770.43 | P2: =_xlfn.XLOOKUP(A:A,Table4_2[Customer ID],Table4_2[Hospital tier]) -> tier - 1 | Q2: =_xlfn.XLOOKUP(A:A,'Hospital details'!A:A,'Hospital details'!F:F) -> tier - 3 | R2: =_xlfn.XLOOKUP(Healthcare!A:A,'Hospital details'!A:A,'Hospital details'!G:G) -> R1013 | S2: =_xlfn.XLOOKUP(A:A,'Hospital details'!A:A,'Hospital details'!H:H) -> 54
A3: Id2 | B3: {=_xlfn.XLOOKUP(_xlfn.SINGLE(A:A),'Customer Name'!A:A,Table14_3[[#All],[Title]])} -> Mr | C3: {=_xlfn.XLOOKUP(_xlfn.SINGLE(A:A),'Customer Name'!A:A,Table14_3[[#All],[First Name]])} -> Matthew D | D3: {=_xlfn.XLOOKUP(_xlfn.SINGLE(A:A),'Customer Name'!A:A,Table14_3[[#All],[Last Name]])} -> Lehner | E3: =_xlfn.XLOOKUP(A:A,'Medical Examination'!A:A,'Medical Examination'!B:B) -> 30.36 | F3: =_xlfn.XLOOKUP(A:A,'Medical Examination'!A:A,'Medical Examination'!C:C) -> 5.77 | G3: =_xlfn.XLOOKUP(A:A,'Medical Examination'!A:A,'Medical Examination'!D:D) -> No | H3: =_xlfn.XLOOKUP(A:A,'Medical Examination'!A:A,'Medical Examination'!E:E) -> No | I3: =_xlfn.XLOOKUP(A:A,'Medical Examination'!A:A,'Medical Examination'!F:F) -> No | J3: =_xlfn.XLOOKUP(A:A,'Medical Examination'!A:A,'Medical Examination'!G:G) -> 0 | K3: =_xlfn.XLOOKUP(A:A,'Medical Examination'!A:A,'Medical Examination'!H:H) -> yes | L3: =_xlfn.XLOOKUP(A:A,'Medical Examination'!A:A,'Medical Examination'!I:I) -> Obesity | M3: =_xlfn.XLOOKUP(A:A,'Medical Examination'!A:A,'Medical Examination'!J:J) -> Prediabetic | N3: =_xlfn.XLOOKUP(Healthcare!A:A,Table4_2[Customer ID],Table4_2[Date of Birth]) -> 28284 | O3: =_xlfn.XLOOKUP(A:A,Table4_2[Customer ID],Table4_2[Charges]) -> 62592.87 | P3: =_xlfn.XLOOKUP(A:A,Table4_2[Customer ID],Table4_2[Hospital tier]) -> tier - 2 | Q3: =_xlfn.XLOOKUP(A:A,'Hospital details'!A:A,'Hospital details'!F:F) -> tier - 3 | R3: =_xlfn.XLOOKUP(Healthcare!A:A,'Hospital details'!A:A,'Hospital details'!G:G) -> R1013 | S3: =_xlfn.XLOOKUP(A:A,'Hospital details'!A:A,'Hospital details'!H:H) -> 46
A4: Id3 | B4: {=_xlfn.XLOOKUP(_xlfn.SINGLE(A:A),'Customer Name'!A:A,Table14_3[[#All],[Title]])} -> Mr | C4: {=_xlfn.XLOOKUP(_xlfn.SINGLE(A:A),'Customer Name'!A:A,Table14_3[[#All],[First Name]])} -> Phil | D4: {=_xlfn.XLOOKUP(_xlfn.SINGLE(A:A),'Customer Name'!A:A,Table14_3[[#All],[Last Name]])} -> Lu | E4: =_xlfn.XLOOKUP(A:A,'Medical Examination'!A:A,'Medical Examination'!B:B) -> 34.485 | F4: =_xlfn.XLOOKUP(A:A,'Medical Examination'!A:A,'Medical Examination'!C:C) -> 11.87 | G4: =_xlfn.XLOOKUP(A:A,'Medical Examination'!A:A,'Medical Examination'!D:D) -> yes | H4: =_xlfn.XLOOKUP(A:A,'Medical Examination'!A:A,'Medical Examination'!E:E) -> No | I4: =_xlfn.XLOOKUP(A:A,'Medical Examination'!A:A,'Medical Examination'!F:F) -> No | J4: =_xlfn.XLOOKUP(A:A,'Medical Examination'!A:A,'Medical Examination'!G:G) -> 2 | K4: =_xlfn.XLOOKUP(A:A,'Medical Examination'!A:A,'Medical Examination'!H:H) -> yes | L4: =_xlfn.XLOOKUP(A:A,'Medical Examination'!A:A,'Medical Examination'!I:I) -> Obesity | M4: =_xlfn.XLOOKUP(A:A,'Medical Examination'!A:A,'Medical Examination'!J:J) -> Diabetic | N4: =_xlfn.XLOOKUP(Healthcare!A:A,Table4_2[Customer ID],Table4_2[Date of Birth]) -> 25822 | O4: =_xlfn.XLOOKUP(A:A,Table4_2[Customer ID],Table4_2[Charges]) -> 60021.4 | P4: =_xlfn.XLOOKUP(A:A,Table4_2[Customer ID],Table4_2[Hospital tier]) -> tier - 1 | Q4: =_xlfn.XLOOKUP(A:A,'Hospital details'!A:A,'Hospital details'!F:F) -> tier - 1 | R4: =_xlfn.XLOOKUP(Healthcare!A:A,'Hospital details'!A:A,'Hospital details'!G:G) -> R1012 | S4: =_xlfn.XLOOKUP(A:A,'Hospital details'!A:A,'Hospital details'!H:H) -> 52
A5: Id4 | B5: {=_xlfn.XLOOKUP(_xlfn.SINGLE(A:A),'Customer Name'!A:A,Table14_3[[#All],[Title]])} -> Ms | C5: {=_xlfn.XLOOKUP(_xlfn.SINGLE(A:A),'Customer Name'!A:A,Table14_3[[#All],[First Name]])} -> Kelsey | D5: {=_xlfn.XLOOKUP(_xlfn.SINGLE(A:A),'Customer Name'!A:A,Table14_3[[#All],[Last Name]])} -> Osborne | E5: =_xlfn.XLOOKUP(A:A,'Medical Examination'!A:A,'Medical Examination'!B:B) -> 38.095 | F5: =_xlfn.XLOOKUP(A:A,'Medical Examination'!A:A,'Medical Examination'!C:C) -> 6.05 | G5: =_xlfn.XLOOKUP(A:A,'Medical Examination'!A:A,'Medical Examination'!D:D) -> No | H5: =_xlfn.XLOOKUP(A:A,'Medical Examination'!A:A,'Medical Examination'!E:E) -> No | I5: =_xlfn.XLOOKUP(A:A,'Medical Examination'!A:A,'Medical Examination'!F:F) -> No | J5: =_xlfn.XLOOKUP(A:A,'Medical Examination'!A:A,'Medical Examination'!G:G) -> 0 | K5: =_xlfn.XLOOKUP(A:A,'Medical Examination'!A:A,'Medical Examination'!H:H) -> yes | L5: =_xlfn.XLOOKUP(A:A,'Medical Examination'!A:A,'Medical Examination'!I:I) -> Obesity | M5: =_xlfn.XLOOKUP(A:A,'Medical Examination'!A:A,'Medical Examination'!J:J) -> Prediabetic | N5: =_xlfn.XLOOKUP(Healthcare!A:A,Table4_2[Customer ID],Table4_2[Date of Birth]) -> 33395 | O5: =_xlfn.XLOOKUP(A:A,Table4_2[Customer ID],Table4_2[Charges]) -> 58571.07 | P5: =_xlfn.XLOOKUP(A:A,Table4_2[Customer ID],Table4_2[Hospital tier]) -> tier - 1 | Q5: =_xlfn.XLOOKUP(A:A,'Hospital details'!A:A,'Hospital details'!F:F) -> tier - 3 | R5: =_xlfn.XLOOKUP(Healthcare!A:A,'Hospital details'!A:A,'Hospital details'!G:G) -> R1024 | S5: =_xlfn.XLOOKUP(A:A,'Hospital details'!A:A,'Hospital details'!H:H) -> 32
A6: Id5 | B6: {=_xlfn.XLOOKUP(_xlfn.SINGLE(A:A),'Customer Name'!A:A,Table14_3[[#All],[Title]])} -> Mr | C6: {=_xlfn.XLOOKUP(_xlfn.SINGLE(A:A),'Customer Name'!A:A,Table14_3[[#All],[First Name]])} -> Kristyn | D6: {=_xlfn.XLOOKUP(_xlfn.SINGLE(A:A),'Customer Name'!A:A,Table14_3[[#All],[Last Name]])} -> Kadala | E6: =_xlfn.XLOOKUP(A:A,'Medical Examination'!A:A,'Medical Examination'!B:B) -> 35.53 | F6: =_xlfn.XLOOKUP(A:A,'Medical Examination'!A:A,'Medical Examination'!C:C) -> 5.45 | G6: =_xlfn.XLOOKUP(A:A,'Medical Examination'!A:A,'Medical Examination'!D:D) -> No | H6: =_xlfn.XLOOKUP(A:A,'Medical Examination'!A:A,'Medical Examination'!E:E) -> No | I6: =_xlfn.XLOOKUP(A:A,'Medical Examination'!A:A,'Medical Examination'!F:F) -> No | J6: =_xlfn.XLOOKUP(A:A,'Medical Examination'!A:A,'Medical Examination'!G:G) -> 0 | K6: =_xlfn.XLOOKUP(A:A,'Medical Examination'!A:A,'Medical Examination'!H:H) -> yes | L6: =_xlfn.XLOOKUP(A:A,'Medical Examination'!A:A,'Medical Examination'!I:I) -> Obesity | M6: =_xlfn.XLOOKUP(A:A,'Medical Examination'!A:A,'Medical Examination'!J:J) -> Normal | N6: =_xlfn.XLOOKUP(Healthcare!A:A,Table4_2[Customer ID],Table4_2[Date of Birth]) -> 32678 | O6: =_xlfn.XLOOKUP(A:A,Table4_2[Customer ID],Table4_2[Charges]) -> 55135.4 | P6: =_xlfn.XLOOKUP(A:A,Table4_2[Customer ID],Table4_2[Hospital tier]) -> tier - 1 | Q6: =_xlfn.XLOOKUP(A:A,'Hospital details'!A:A,'Hospital details'!F:F) -> tier - 2 | R6: =_xlfn.XLOOKUP(Healthcare!A:A,'Hospital details'!A:A,'Hospital details'!G:G) -> R1012 | S6: =_xlfn.XLOOKUP(A:A,'Hospital details'!A:A,'Hospital details'!H:H) -> 33
A7: Id6 | B7: {=_xlfn.XLOOKUP(_xlfn.SINGLE(A:A),'Customer Name'!A:A,Table14_3[[#All],[Title]])} -> Mr | C7: {=_xlfn.XLOOKUP(_xlfn.SINGLE(A:A),'Customer Name'!A:A,Table14_3[[#All],[First Name]])} -> Russell B | D7: {=_xlfn.XLOOKUP(_xlfn.SINGLE(A:A),'Customer Name'!A:A,Table14_3[[#All],[Last Name]])} -> Baker | E7: =_xlfn.XLOOKUP(A:A,'Medical Examination'!A:A,'Medical Examination'!B:B) -> 32.8 | F7: =_xlfn.XLOOKUP(A:A,'Medical Examination'!A:A,'Medical Examination'!C:C) -> 6.59 | G7: =_xlfn.XLOOKUP(A:A,'Medical Examination'!A:A,'Medical Examination'!D:D) -> No | H7: =_xlfn.XLOOKUP(A:A,'Medical Examination'!A:A,'Medical Examination'!E:E) -> No | I7: =_xlfn.XLOOKUP(A:A,'Medical Examination'!A:A,'Medical Examination'!F:F) -> No | J7: =_xlfn.XLOOKUP(A:A,'Medical Examination'!A:A,'Medical Examination'!G:G) -> 0 | K7: =_xlfn.XLOOKUP(A:A,'Medical Examination'!A:A,'Medical Examination'!H:H) -> yes | L7: =_xlfn.XLOOKUP(A:A,'Medical Examination'!A:A,'Medical Examination'!I:I) -> Obesity | M7: =_xlfn.XLOOKUP(A:A,'Medical Examination'!A:A,'Medical Examination'!J:J) -> Diabetic | N7: =_xlfn.XLOOKUP(Healthcare!A:A,Table4_2[Customer ID],Table4_2[Date of Birth]) -> 22862 | O7: =_xlfn.XLOOKUP(A:A,Table4_2[Customer ID],Table4_2[Charges]) -> 52590.83 | P7: =_xlfn.XLOOKUP(A:A,Table4_2[Customer ID],Table4_2[Hospital tier]) -> tier - 1 | Q7: =_xlfn.XLOOKUP(A:A,'Hospital details'!A:A,'Hospital details'!F:F) -> tier - 3 | R7: =_xlfn.XLOOKUP(Healthcare!A:A,'Hospital details'!A:A,'Hospital details'!G:G) -> R1011 | S7: =_xlfn.XLOOKUP(A:A,'Hospital details'!A:A,'Hospital details'!H:H) -> 60
A8: Id7 | B8: {=_xlfn.XLOOKUP(_xlfn.SINGLE(A:A),'Customer Name'!A:A,Table14_3[[#All],[Title]])} -> Ms | C8: {=_xlfn.XLOOKUP(_xlfn.SINGLE(A:A),'Customer Name'!A:A,Table14_3[[#All],[First Name]])} -> Scott | D8: {=_xlfn.XLOOKUP(_xlfn.SINGLE(A:A),'Customer Name'!A:A,Table14_3[[#All],[Last Name]])} -> Macpherson | E8: =_xlfn.XLOOKUP(A:A,'Medical Examination'!A:A,'Medical Examination'!B:B) -> 36.4 | F8: =_xlfn.XLOOKUP(A:A,'Medical Examination'!A:A,'Medical Examination'!C:C) -> 6.07 | G8: =_xlfn.XLOOKUP(A:A,'Medical Examination'!A:A,'Medical Examination'!D:D) -> No | H8: =_xlfn.XLOOKUP(A:A,'Medical Examination'!A:A,'Medical Examination'!E:E) -> No | I8: =_xlfn.XLOOKUP(A:A,'Medical Examination'!A:A,'Medical Examination'!F:F) -> No | J8: =_xlfn.XLOOKUP(A:A,'Medical Examination'!A:A,'Medical Examination'!G:G) -> 0 | K8: =_xlfn.XLOOKUP(A:A,'Medical Examination'!A:A,'Medical Examination'!H:H) -> yes | L8: =_xlfn.XLOOKUP(A:A,'Medical Examination'!A:A,'Medical Examination'!I:I) -> Obesity | M8: =_xlfn.XLOOKUP(A:A,'Medical Examination'!A:A,'Medical Examination'!J:J) -> Prediabetic | N8: =_xlfn.XLOOKUP(Healthcare!A:A,Table4_2[Customer ID],Table4_2[Date of Birth]) -> 34634 | O8: =_xlfn.XLOOKUP(A:A,Table4_2[Customer ID],Table4_2[Charges]) -> 51194.56 | P8: =_xlfn.XLOOKUP(A:A,Table4_2[Customer ID],Table4_2[Hospital tier]) -> tier - 1 | Q8: =_xlfn.XLOOKUP(A:A,'Hospital details'!A:A,'Hospital details'!F:F) -> tier - 3 | R8: =_xlfn.XLOOKUP(Healthcare!A:A,'Hospital details'!A:A,'Hospital details'!G:G) -> R1011 | S8: =_xlfn.XLOOKUP(A:A,'Hospital details'!A:A,'Hospital details'!H:H) -> 28
A9: Id8 | B9: {=_xlfn.XLOOKUP(_xlfn.SINGLE(A:A),'Customer Name'!A:A,Table14_3[[#All],[Title]])} -> Mr | C9: {=_xlfn.XLOOKUP(_xlfn.SINGLE(A:A),'Customer Name'!A:A,Table14_3[[#All],[First Name]])} -> Stephen | D9: {=_xlfn.XLOOKUP(_xlfn.SINGLE(A:A),'Customer Name'!A:A,Table14_3[[#All],[Last Name]])} -> Hallman | E9: =_xlfn.XLOOKUP(A:A,'Medical Examination'!A:A,'Medical Examination'!B:B) -> 36.96 | F9: =_xlfn.XLOOKUP(A:A,'Medical Examination'!A:A,'Medical Examination'!C:C) -> 7.93 | G9: =_xlfn.XLOOKUP(A:A,'Medical Examination'!A:A,'Medical Examination'!D:D) -> No | H9: =_xlfn.XLOOKUP(A:A,'Medical Examination'!A:A,'Medical Examination'!E:E) -> No | I9: =_xlfn.XLOOKUP(A:A,'Medical Examination'!A:A,'Medical Examination'!F:F) -> No | J9: =_xlfn.XLOOKUP(A:A,'Medical Examination'!A:A,'Medical Examination'!G:G) -> 3 | K9: =_xlfn.XLOOKUP(A:A,'Medical Examination'!A:A,'Medical Examination'!H:H) -> yes | L9: =_xlfn.XLOOKUP(A:A,'Medical Examination'!A:A,'Medical Examination'!I:I) -> Obesity | M9: =_xlfn.XLOOKUP(A:A,'Medical Examination'!A:A,'Medical Examination'!J:J) -> Diabetic | N9: =_xlfn.XLOOKUP(Healthcare!A:A,Table4_2[Customer ID],Table4_2[Date of Birth]) -> 21363 | O9: =_xlfn.XLOOKUP(A:A,Table4_2[Customer ID],Table4_2[Charges]) -> 49577.66 | P9: =_xlfn.XLOOKUP(A:A,Table4_2[Customer ID],Table4_2[Hospital tier]) -> tier - 2 | Q9: =_xlfn.XLOOKUP(A:A,'Hospital details'!A:A,'Hospital details'!F:F) -> tier - 2 | R9: =_xlfn.XLOOKUP(Healthcare!A:A,'Hospital details'!A:A,'Hospital details'!G:G) -> R1013 | S9: =_xlfn.XLOOKUP(A:A,'Hospital details'!A:A,'Hospital details'!H:H) -> 64
A10: Id9 | B10: {=_xlfn.XLOOKUP(_xlfn.SINGLE(A:A),'Customer Name'!A:A,Table14_3[[#All],[Title]])} -> Mr | C10: {=_xlfn.XLOOKUP(_xlfn.SINGLE(A:A),'Customer Name'!A:A,Table14_3[[#All],[First Name]])} -> Patrick R | D10: {=_xlfn.XLOOKUP(_xlfn.SINGLE(A:A),'Customer Name'!A:A,Table14_3[[#All],[Last Name]])} -> Moran | E10: =_xlfn.XLOOKUP(A:A,'Medical Examination'!A:A,'Medical Examination'!B:B) -> 41.14 | F10: =_xlfn.XLOOKUP(A:A,'Medical Examination'!A:A,'Medical Examination'!C:C) -> 9.58 | G10: =_xlfn.XLOOKUP(A:A,'Medical Examination'!A:A,'Medical Examination'!D:D) -> yes | H10: =_xlfn.XLOOKUP(A:A,'Medical Examination'!A:A,'Medical Examination'!E:E) -> No | I10: =_xlfn.XLOOKUP(A:A,'Medical Examination'!A:A,'Medical Examination'!F:F) -> Yes | J10: =_xlfn.XLOOKUP(A:A,'Medical Examination'!A:A,'Medical Examination'!G:G) -> 1 | K10: =_xlfn.XLOOKUP(A:A,'Medical Examination'!A:A,'Medical Examination'!H:H) -> yes | L10: =_xlfn.XLOOKUP(A:A,'Medical Examination'!A:A,'Medical Examination'!I:I) -> Obesity | M10: =_xlfn.XLOOKUP(A:A,'Medical Examination'!A:A,'Medical Examination'!J:J) -> Diabetic | N10: =_xlfn.XLOOKUP(Healthcare!A:A,Table4_2[Customer ID],Table4_2[Date of Birth]) -> 23258 | O10: =_xlfn.XLOOKUP(A:A,Table4_2[Customer ID],Table4_2[Charges]) -> 48970.25 | P10: =_xlfn.XLOOKUP(A:A,Table4_2[Customer ID],Table4_2[Hospital tier]) -> tier - 1 | Q10: =_xlfn.XLOOKUP(A:A,'Hospital details'!A:A,'Hospital details'!F:F) -> tier - 2 | R10: =_xlfn.XLOOKUP(Healthcare!A:A,'Hospital details'!A:A,'Hospital details'!G:G) -> R1013 | S10: =_xlfn.XLOOKUP(A:A,'Hospital details'!A:A,'Hospital details'!H:H) -> 59
A11: Id10 | B11: {=_xlfn.XLOOKUP(_xlfn.SINGLE(A:A),'Customer Name'!A:A,Table14_3[[#All],[Title]])} -> Ms | C11: {=_xlfn.XLOOKUP(_xlfn.SINGLE(A:A),'Customer Name'!A:A,Table14_3[[#All],[First Name]])} -> Brooke N | D11: {=_xlfn.XLOOKUP(_xlfn.SINGLE(A:A),'Customer Name'!A:A,Table14_3[[#All],[Last Name]])} -> Benner | E11: =_xlfn.XLOOKUP(A:A,'Medical Examination'!A:A,'Medical Examination'!B:B) -> 38.06 | F11: =_xlfn.XLOOKUP(A:A,'Medical Examination'!A:A,'Medical Examination'!C:C) -> 10.79 | G11: =_xlfn.XLOOKUP(A:A,'Medical Examination'!A:A,'Medical Examination'!D:D) -> No | H11: =_xlfn.XLOOKUP(A:A,'Medical Examination'!A:A,'Medical Examination'!E:E) -> No | I11: =_xlfn.XLOOKUP(A:A,'Medical Examination'!A:A,'Medical Examination'!F:F) -> No | J11: =_xlfn.XLOOKUP(A:A,'Medical Examination'!A:A,'Medical Examination'!G:G) -> 0 | K11: =_xlfn.XLOOKUP(A:A,'Medical Examination'!A:A,'Medical Examination'!H:H) -> yes | L11: =_xlfn.XLOOKUP(A:A,'Medical Examination'!A:A,'Medical Examination'!I:I) -> Obesity | M11: =_xlfn.XLOOKUP(A:A,'Medical Examination'!A:A,'Medical Examination'!J:J) -> Diabetic | N11: =_xlfn.XLOOKUP(Healthcare!A:A,Table4_2[Customer ID],Table4_2[Date of Birth]) -> 28853 | O11: =_xlfn.XLOOKUP(A:A,Table4_2[Customer ID],Table4_2[Charges]) -> 48885.14 | P11: =_xlfn.XLOOKUP(A:A,Table4_2[Customer ID],Table4_2[Hospital tier]) -> tier - 1 | Q11: =_xlfn.XLOOKUP(A:A,'Hospital details'!A:A,'Hospital details'!F:F) -> tier - 2 | R11: =_xlfn.XLOOKUP(Healthcare!A:A,'Hospital details'!A:A,'Hospital details'!G:G) -> R1013 | S11: =_xlfn.XLOOKUP(A:A,'Hospital details'!A:A,'Hospital details'!H:H) -> 44
A12: Id11 | B12: {=_xlfn.XLOOKUP(_xlfn.SINGLE(A:A),'Customer Name'!A:A,Table14_3[[#All],[Title]])} -> Mr | C12: {=_xlfn.XLOOKUP(_xlfn.SINGLE(A:A),'Customer Name'!A:A,Table14_3[[#All],[First Name]])} -> Paola Andrea | D12: {=_xlfn.XLOOKUP(_xlfn.SINGLE(A:A),'Customer Name'!A:A,Table14_3[[#All],[Last Name]])} -> Fierro Vargas | E12: =_xlfn.XLOOKUP(A:A,'Medical Examination'!A:A,'Medical Examination'!B:B) -> 37.7 | F12: =_xlfn.XLOOKUP(A:A,'Medical Examination'!A:A,'Medical Examination'!C:C) -> 5.96 | G12: =_xlfn.XLOOKUP(A:A,'Medical Examination'!A:A,'Medical Examination'!D:D) -> yes | H12: =_xlfn.XLOOKUP(A:A,'Medical Examination'!A:A,'Medical Examination'!E:E) -> No | I12: =_xlfn.XLOOKUP(A:A,'Medical Examination'!A:A,'Medical Examination'!F:F) -> No | J12: =_xlfn.XLOOKUP(A:A,'Medical Examination'!A:A,'Medical Examination'!G:G) -> 2 | K12: =_xlfn.XLOOKUP(A:A,'Medical Examination'!A:A,'Medical Examination'!H:H) -> yes | L12: =_xlfn.XLOOKUP(A:A,'Medical Examination'!A:A,'Medical Examination'!I:I) -> Obesity | M12: =_xlfn.XLOOKUP(A:A,'Medical Examination'!A:A,'Medical Examination'!J:J) -> Prediabetic | N12: =_xlfn.XLOOKUP(Healthcare!A:A,Table4_2[Customer ID],Table4_2[Date of Birth]) -> 21753 | O12: =_xlfn.XLOOKUP(A:A,Table4_2[Customer ID],Table4_2[Charges]) -> 48824.45 | P12: =_xlfn.XLOOKUP(A:A,Table4_2[Customer ID],Table4_2[Hospital tier]) -> tier - 2 | Q12: =_xlfn.XLOOKUP(A:A,'Hospital details'!A:A,'Hospital details'!F:F) -> tier - 1 | R12: =_xlfn.XLOOKUP(Healthcare!A:A,'Hospital details'!A:A,'Hospital details'!G:G) -> R1011 | S12: =_xlfn.XLOOKUP(A:A,'Hospital details'!A:A,'Hospital details'!H:H) -> 63
A13: Id12 | B13: {=_xlfn.XLOOKUP(_xlfn.SINGLE(A:A),'Customer Name'!A:A,Table14_3[[#All],[Title]])} -> Mr | C13: {=_xlfn.XLOOKUP(_xlfn.SINGLE(A:A),'Customer Name'!A:A,Table14_3[[#All],[First Name]])} -> David | D13: {=_xlfn.XLOOKUP(_xlfn.SINGLE(A:A),'Customer Name'!A:A,Table14_3[[#All],[Last Name]])} -> Franz | E13: =_xlfn.XLOOKUP(A:A,'Medical Examination'!A:A,'Medical Examination'!B:B) -> 42.13 | F13: =_xlfn.XLOOKUP(A:A,'Medical Examination'!A:A,'Medical Examination'!C:C) -> 11.9 | G13: =_xlfn.XLOOKUP(A:A,'Medical Examination'!A:A,'Medical Examination'!D:D) -> No | H13: =_xlfn.XLOOKUP(A:A,'Medical Examination'!A:A,'Medical Examination'!E:E) -> No | I13: =_xlfn.XLOOKUP(A:A,'Medical Examination'!A:A,'Medical Examination'!F:F) -> No | J13: =_xlfn.XLOOKUP(A:A,'Medical Examination'!A:A,'Medical Examination'!G:G) -> 0 | K13: =_xlfn.XLOOKUP(A:A,'Medical Examination'!A:A,'Medical Examination'!H:H) -> yes | L13: =_xlfn.XLOOKUP(A:A,'Medical Examination'!A:A,'Medical Examination'!I:I) -> Obesity | M13: =_xlfn.XLOOKUP(A:A,'Medical Examination'!A:A,'Medical Examination'!J:J) -> Diabetic | N13: =_xlfn.XLOOKUP(Healthcare!A:A,Table4_2[Customer ID],Table4_2[Date of Birth]) -> 24042 | O13: =_xlfn.XLOOKUP(A:A,Table4_2[Customer ID],Table4_2[Charges]) -> 48675.52 | P13: =_xlfn.XLOOKUP(A:A,Table4_2[Customer ID],Table4_2[Hospital tier]) -> tier - 1 | Q13: =_xlfn.XLOOKUP(A:A,'Hospital details'!A:A,'Hospital details'!F:F) -> tier - 2 | R13: =_xlfn.XLOOKUP(Healthcare!A:A,'Hospital details'!A:A,'Hospital details'!G:G) -> R1013 | S13: =_xlfn.XLOOKUP(A:A,'Hospital details'!A:A,'Hospital details'!H:H) -> 57
... A2336: Id2335 | B2336: {=_xlfn.XLOOKUP(_xlfn.SINGLE(A:A),'Customer Name'!A:A,Table14_3[[#All],[Title]])} -> Ms | C2336: {=_xlfn.XLOOKUP(_xlfn.SINGLE(A:A),'Customer Name'!A:A,Table14_3[[#All],[First Name]])} -> Aaron K | D2336: {=_xlfn.XLOOKUP(_xlfn.SINGLE(A:A),'Customer Name'!A:A,Table14_3[[#All],[Last Name]])} -> German | E2336: =_xlfn.XLOOKUP(A:A,'Medical Examination'!A:A,'Medical Examination'!B:B) -> 17.58 | F2336: =_xlfn.XLOOKUP(A:A,'Medical Examination'!A:A,'Medical Examination'!C:C) -> 4.51 | G2336: =_xlfn.XLOOKUP(A:A,'Medical Examination'!A:A,'Medical Examination'!D:D) -> No | H2336: =_xlfn.XLOOKUP(A:A,'Medical Examination'!A:A,'Medical Examination'!E:E) -> No | I2336: =_xlfn.XLOOKUP(A:A,'Medical Examination'!A:A,'Medical Examination'!F:F) -> No | J2336: =_xlfn.XLOOKUP(A:A,'Medical Examination'!A:A,'Medical Examination'!G:G) -> 1 | K2336: =_xlfn.XLOOKUP(A:A,'Medical Examination'!A:A,'Medical Examination'!H:H) -> No | L2336: =_xlfn.XLOOKUP(A:A,'Medical Examination'!A:A,'Medical Examination'!I:I) -> Under Weight | M2336: =_xlfn.XLOOKUP(A:A,'Medical Examination'!A:A,'Medical Examination'!J:J) -> Normal | N2336: =_xlfn.XLOOKUP(Healthcare!A:A,Table4_2[Customer ID],Table4_2[Date of Birth]) -> 33794 | O2336: =_xlfn.XLOOKUP(A:A,Table4_2[Customer ID],Table4_2[Charges]) -> 563.84 | P2336: =_xlfn.XLOOKUP(A:A,Table4_2[Customer ID],Table4_2[Hospital tier]) -> tier - 2 | Q2336: =_xlfn.XLOOKUP(A:A,'Hospital details'!A:A,'Hospital details'!F:F) -> tier - 3 | R2336: =_xlfn.XLOOKUP(Healthcare!A:A,'Hospital details'!A:A,'Hospital details'!G:G) -> R1013 | S2336: =_xlfn.XLOOKUP(A:A,'Hospital details'!A:A,'Hospital details'!H:H) -> 30
A2337: =SUBTOTAL(103,Table3[Customer ID]) -> 2335 | E2337: =SUBTOTAL(101,Table3[BMI]) -> 30.972649 | F2337: =SUBTOTAL(101,Table3[HBAIC]) -> 6.5789979 | J2337: =SUBTOTAL(109,Table3[Number of major Surgeries]) -> 1579 | O2337: =SUBTOTAL(101,Table3[Charges]) -> 13529.918

Sheet GPT cache
GB967863: {"hash":"ecbec4b66f6640b7b7eef0746219de145b43946fdf699e2251914f0e38fe2f85","version":1,"value":"[[\"=COUNTIF(A:A, U2)\"]]"}

Sheet Manual Pivot Table
A1: Smoker And Non-Smoker pivot Table | H1: Charges by Weight Status | K1: No of Surgeries in hospital Tier
H4: Weight status | I4: Sum of Charges | K4: Sum of Charges | L4: No of surgery
A5: Count of Customer ID | B5: Cancer History | H5: Under Weight | I5: 1214279.9 | K5: Hospital Tier | L5: 0 | M5: 1 | N5: 2 | O5: 3 | P5: Grand Total
A6: Somker | B6: No | C6: Grand Total | H6: Normal Weight | I6: 4305290.1 | K6: tier - 1 | L6: 4482139.3 | M6: 3419941 | N6: 1197698.4 | O6: 59497.6 | P6: 9159276.4
A7: No | B7: 1540 | C7: 1540 | H7: Obesity | I7: 20343647 | K7: tier - 2 | L7: 7210299.9 | M7: 6071425.4 | N7: 2169094.2 | O7: 424910.16 | P7: 15875730
A8: yes | B8: 404 | C8: 404 | H8: Over Weight | I8: 5729141.8 | K8: tier - 3 | L8: 3005254.8 | M8: 2285988.3 | N8: 1238455.6 | O8: 27653.92 | P8: 6557352.6
A9: Grand Total | B9: 1944 | C9: 1944 | H9: Grand Total | I9: 31592359 | K9: Grand Total | L9: 14697694 | M9: 11777355 | N9: 4605248.2 | O9: 512061.68 | P9: 31592359

Sheet Cost & Metrics Analysis
F1: Quick Analysis
A3: Total customers count, | B3: 2335 | E3: QUICK ANALYSIS - CUSTOMER METRICS
A4: Total hospitalisation count | B4: 2335
A5: Total Surgeries | B5: 1579 | E5: Metric | F5: Count | G5: Percentage
A6: Average costs and medical metrics | B6: =SUBTOTAL(101,Table3[Charges]) -> 13529.918 | E6: Total Customers | F6: =COUNTA(Healthcare!A:A)-2 -> 2335 | G6: 1
A7: Medical metrics (BMI) | B7: =SUBTOTAL(101,Table3[BMI]) -> 30.972649
A8: Medical metrics (HBA1C) | B8: =SUBTOTAL(101,Table3[HBAIC]) -> 6.5789979 | E8: CUSTOMER BREAKDOWN BY KEY METRICS
A9: Total healthcare costs, | B9: =SUBTOTAL(109,Table3[Charges]) -> 31592359
E10: Smokers | F10: =COUNTIF(Healthcare!K:K,"yes") -> 488 | G10: =COUNTIF(Healthcare!K:K,"yes")/(COUNTA(Healthcare!A:A)-1) -> 0.20890411
E11: Non-Smokers | F11: =COUNTIF(Healthcare!K:K,"no") -> 1847 | G11: =COUNTIF(Healthcare!K:K,"no")/(COUNTA(Healthcare!A:A)-1) -> 0.79066781
E13: Obesity | F13: =COUNTIF(Healthcare!L:L,"Obesity") -> 1221 | G13: =COUNTIF(Healthcare!L:L,"Obesity")/(COUNTA(Healthcare!A:A)-1) -> 0.52268836
E14: Normal Weight | F14: =COUNTIF(Healthcare!L:L,"Normal") -> 0 | G14: =COUNTIF(Healthcare!L:L,"Normal")/(COUNTA(Healthcare!A:A)-1) -> 0
E16: Cancer History - Yes | F16: =COUNTIF(Healthcare!I:I,"Yes") -> 391 | G16: =COUNTIF(Healthcare!I:I,"Yes")/(COUNTA(Healthcare!A:A)-1) -> 0.16738014
E17: Cancer History - No | F17: =COUNTIF(Healthcare!I:I,"No") -> 1944 | G17: =COUNTIF(Healthcare!I:I,"No")/(COUNTA(Healthcare!A:A)-1) -> 0.83219178
E19: Heart Disease - Yes | F19: =COUNTIF(Healthcare!G:G,"yes") -> 926 | G19: =COUNTIF(Healthcare!G:G,"yes")/(COUNTA(Healthcare!A:A)-1) -> 0.39640411
E20: Heart Disease - No | F20: =COUNTIF(Healthcare!G:G,"No") -> 1409 | G20: =COUNTIF(Healthcare!G:G,"No")/(COUNTA(Healthcare!A:A)-1) -> 0.60316781
E22: Diabetic | F22: =COUNTIF(Healthcare!M:M,"Diabetic") -> 784 | G22: =COUNTIF(Healthcare!M:M,"Diabetic")/(COUNTA(Healthcare!A:A)-1) -> 0.33561644
E23: Prediabetic | F23: =COUNTIF(Healthcare!M:M,"Prediabetic") -> 456 | G23: =COUNTIF(Healthcare!M:M,"Prediabetic")/(COUNTA(Healthcare!A:A)-1) -> 0.19520548
E24: Normal Diabetic Status | F24: =COUNTIF(Healthcare!M:M,"Normal") -> 1095 | G24: =COUNTIF(Healthcare!M:M,"Normal")/(COUNTA(Healthcare!A:A)-1) -> 0.46875

Sheet Healthcare Dash Board
A1: Healthcare Dashboard – AI Analysis
